Metadata-Version: 2.1
Name: ovos-tts-plugin-google-tx
Version: 1.0.3
Summary: google translate tts plugin for OVOS
Home-page: https://github.com/OpenVoiceOS/ovos-tts-plugin-google-tx
Author: JarbasAi
Author-email: jarbasai@mailfence.com
License: Apache-2.0
Keywords: mycroft OpenVoiceOS OVOS google translate plugin tts
Classifier: Development Status :: 3 - Alpha
Classifier: Intended Audience :: Developers
Classifier: Topic :: Text Processing :: Linguistic
Classifier: License :: OSI Approved :: Apache Software License
Classifier: Programming Language :: Python :: 3.7
Classifier: Programming Language :: Python :: 3.8
Classifier: Programming Language :: Python :: 3.9
License-File: LICENSE
Requires-Dist: ovos-plugin-manager<2.0.0,>=1.0.0
Requires-Dist: gTTS
